{
    "restaurants": [
        {
            "id": "a7k9m2p4q8r1s3",
            "name": "بيرقلي",
            "image": "https://images.unsplash.com/photo-1571091718767-18b5b1457add?w=800&q=80",
            "description": " ресторан برقر يقدم مجموعة متنوعة من الأطباق المحلوة.",
            "menu": [
                {
                    "id": 1,
                    "name": "وجبة برقر غنم",
                    "price": 50,
                    "category": "طعام",
                    "description": "وجبة لحم غنم مشوي مع صوص خاص وسلطة جانبية.",
                    "image": "https://images.unsplash.com/photo-1550547660-d9450f859349?w=800&q=80",
                    "differents": [
                        { "id": 1, "name": "برجر غنم صغير", "price": 45 },
                        { "id": 2, "name": "برجر غنم كبير", "price": 55 },
                        { "id": 3, "name": "برجر غنم متوسط", "price": 50 },
                        { "id": 4, "name": "برجر غنم كبير جدا", "price": 65 },
                        { "id": 5, "name": "برجر غنم حجم عالي", "price": 70 }
                    ],
                    "addons": [
                        { "id": 1, "name": "بطاطس", "price": 10 },
                        { "id": 2, "name": "مشروب غازي", "price": 8 }
                    ]
                },
                {
                    "id": 2,
                    "name": "2وجبة برقر غنم",
                    "price": 50,
                    "category": "طعام",
                    "description": "وجبة لحم غنم مشوي مع صوص خاص وسلطة جانبية.",
                    "image": "https://images.unsplash.com/photo-1550547660-d9450f859349?w=800&q=80",
                    "differents": [
                        { "id": 1, "name": "برجر غنم صغير", "price": 45 },
                        { "id": 2, "name": "برجر غنم كبير", "price": 55 },
                        { "id": 3, "name": "برجر غنم متوسط", "price": 50 },
                        { "id": 4, "name": "برجر غنم كبير جدا", "price": 65 },
                        { "id": 5, "name": "برجر غنم حجم عالي", "price": 70 }
                    ],
                    "addons": [
                        { "id": 1, "name": "بطاطس", "price": 10 },
                        { "id": 2, "name": "مشروب غازي", "price": 8 }
                    ]
                },
                {
                    "id": 3,
                    "name": "3وجبة برقر غنم",
                    "price": 50,
                    "category": "1طعام",
                    "description": "2وجبة لحم غنم مشوي مع صوص خاص وسلطة جانبية.",
                    "image": "https://images.unsplash.com/photo-1550547660-d9450f859349?w=800&q=80",
                    "differents": [
                        { "id": 1, "name": "برجر غنم صغير", "price": 45 },
                        { "id": 2, "name": "برجر غنم كبير", "price": 55 },
                        { "id": 3, "name": "برجر غنم متوسط", "price": 50 },
                        { "id": 4, "name": "برجر غنم كبير جدا", "price": 65 },
                        { "id": 5, "name": "برجر غنم حجم عالي", "price": 70 }
                    ],
                    "addons": [
                        { "id": 1, "name": "بطاطس", "price": 10 },
                        { "id": 2, "name": "مشروب غازي", "price": 8 }
                    ]
                }
            ],
            "branches": [
                { "id": 1, "name": "وسط البلد", "address": "123 شارع التحرير", "phone": "+201234567890" },
                { "id": 2, "name": "مدينة نصر", "address": "45 شارع الطيران", "phone": "+201098765432" }
            ]
        },
        {
            "id": "b3n5t7v9w2x4y6",
            "name": "Burger King",
            "image": "https://images.unsplash.com/photo-1571091718767-18b5b1457add?w=800&q=80",
            "description": "Burger King is a fast-food chain known for its burgers and fries.",
            "menu": [
                {
                    "id": 1,
                    "name": "1Whopper",
                    "price": 60,
                    "category": "1Fast Food",
                    "description": "1ساندوتش Whopper الشهير بلحم البقر الطازج.",
                    "image": "https://images.unsplash.com/photo-1550547660-d9450f859349?w=800&q=80",
                    "differents": [
                        { "id": 1, "name": "Whopper Classic", "price": 60 },
                        { "id": 2, "name": "Double Whopper", "price": 75 }
                    ],
                    "addons": [
                        { "id": 1, "name": "جبنة إضافية", "price": 5 },
                        { "id": 2, "name": "بطاطس كبيرة", "price": 12 }
                    ]
                },
                {
                    "id": 2,
                    "name": "2Whopper",
                    "price": 60,
                    "category": "2Fast Food",
                    "description": "2ساندوتش Whopper الشهير بلحم البقر الطازج.",
                    "image": "https://images.unsplash.com/photo-1550547660-d9450f859349?w=800&q=80",
                    "differents": [
                        { "id": 1, "name": "Whopper Classic", "price": 60 },
                        { "id": 2, "name": "Double Whopper", "price": 75 }
                    ],
                    "addons": [
                        { "id": 1, "name": "جبنة إضافية", "price": 5 },
                        { "id": 2, "name": "بطاطس كبيرة", "price": 12 }
                    ]
                },
                {
                    "id": 3,
                    "name": "3Whopper",
                    "price": 60,
                    "category": "3Fast Food",
                    "description": "3ساندوتش Whopper الشهير بلحم البقر الطازج.",
                    "image": "https://images.unsplash.com/photo-1550547660-d9450f859349?w=800&q=80",
                    "differents": [
                        { "id": 1, "name": "Whopper Classic", "price": 60 },
                        { "id": 2, "name": "Double Whopper", "price": 75 }
                    ],
                    "addons": [
                        { "id": 1, "name": "جبنة إضافية", "price": 5 },
                        { "id": 2, "name": "بطاطس كبيرة", "price": 12 }
                    ]
                }
            ],
            "branches": [
                { "id": 1, "name": "المهندسين", "address": "شارع جامعة الدول", "phone": "+201115554444" },
                { "id": 2, "name": "الهرم", "address": "شارع الهرم الرئيسي", "phone": "+201334455667" }
            ]
        },
        {
            "id": "c8f1h3j5l7m9n2",
            "name": "بيتزا هت",
            "image": "https://images.unsplash.com/photo-1513104890138-7c749659a591?w=800&q=80",
            "description": "بيتزا هت هي متجر بيتزا يوفر مجموعة متنوعة من أنواع البيتزا.",

            "menu": [
                {
                    "id": 1,
                    "name": "بيتزا سوبر سوبريم",
                    "price": 85,
                    "category": "بيتزا",
                    "description": "بيتزا مليئة باللحم والزيتون والفلفل الأخضر.",
                    "image": "https://images.unsplash.com/photo-1565299624946-b28f40a0ae38?w=800&q=80",
                    "differents": [
                        { "id": 1, "name": "صغيرة", "price": 55 },
                        { "id": 2, "name": "متوسطة", "price": 75 },
                        { "id": 3, "name": "كبيرة", "price": 90 }
                    ],
                    "addons": [
                        { "id": 1, "name": "إضافة جبنة", "price": 10 },
                        { "id": 2, "name": "صوص رانش", "price": 5 }
                    ]
                }
            ],
            "branches": [
                { "id": 1, "name": "التجمع الخامس", "address": "شارع التسعين", "phone": "+201222333444" },
                { "id": 2, "name": "مدينة نصر", "address": "شارع مكرم عبيد", "phone": "+201233344455" }
            ]
        },
        {
            "id": "d4g6i8k0o2p4q6",
            "name": "ماكدونالدز",
            "image": "https://images.unsplash.com/photo-1571091718767-18b5b1457add?w=800&q=80",
            "description": " McAfee is a fast-food chain known for its hamburgers and French fries.",

            "menu": [
                {
                    "id": 1,
                    "name": "Big Mac",
                    "price": 65,
                    "category": "Fast Food",
                    "description": "برجر لحم مع صوص خاص وخس طازج.",
                    "image": "https://images.unsplash.com/photo-1550547660-d9450f859349?w=800&q=80",
                    "differents": [
                        { "id": 1, "name": "Big Mac عادي", "price": 65 },
                        { "id": 2, "name": "Double Big Mac", "price": 80 }
                    ],
                    "addons": [
                        { "id": 1, "name": "بطاطس", "price": 12 },
                        { "id": 2, "name": "كولا", "price": 10 }
                    ]
                }
            ],
            "branches": [
                { "id": 1, "name": "وسط البلد", "address": "شارع قصر النيل", "phone": "+201000111222" },
                { "id": 2, "name": "المعادي", "address": "شارع اللاسلكي", "phone": "+201055566677" }
            ]
        },
        {
            "id": "e9h1j3l5n7p9r1",
            "name": "كنتاكي",
            "image": "https://images.unsplash.com/photo-1626082927389-6cd097cdc6ec?w=800&q=80",
            "description": "Kentucky is a fast-food chain known for its fried chicken and waffles.",
            "menu": [
                {
                    "id": 1,
                    "name": "وجبة زنجر بوكس",
                    "price": 70,
                    "category": "وجبات",
                    "description": "وجبة زنجر مقلية مع صوص الثوم وبطاطس.",
                    "image": "https://images.unsplash.com/photo-1626645738196-c2a7c87a8f58?w=800&q=80",
                    "differents": [
                        { "id": 1, "name": "وجبة عادية", "price": 70 },
                        { "id": 2, "name": "وجبة حارة", "price": 75 }
                    ],
                    "addons": [
                        { "id": 1, "name": "كولا", "price": 8 },
                        { "id": 2, "name": "بطاطس", "price": 10 }
                    ]
                }
            ],
            "branches": [
                { "id": 1, "name": "مصر الجديدة", "address": "شارع النزهة", "phone": "+201223344556" },
                { "id": 2, "name": "الدقي", "address": "شارع التحرير", "phone": "+201144455566" }
            ]
        },
        {
            "id": "f5i7k9m1o3q5s7",
            "name": "TGI Friday's",
            "image": "https://images.unsplash.com/photo-1546833999-b9f581a1996d?w=800&q=80",
            "description": "TGI Friday’s is a chain of American restaurants specializing in American cuisine.",
            "menu": [
                {
                    "id": 1,
                    "name": "ستيك كلاسيك",
                    "price": 120,
                    "category": "لحوم",
                    "description": "قطعة لحم بقري مشوي مع بطاطس مهروسة وصوص.",
                    "image": "https://images.unsplash.com/photo-1544025162-d76694265947?w=800&q=80",
                    "differents": [
                        { "id": 1, "name": "Medium Rare", "price": 120 },
                        { "id": 2, "name": "Well Done", "price": 125 }
                    ],
                    "addons": [
                        { "id": 1, "name": "صوص إضافي", "price": 10 },
                        { "id": 2, "name": "خضار سوتيه", "price": 15 }
                    ]
                }
            ],
            "branches": [
                { "id": 1, "name": "التجمع", "address": "شارع التسعين", "phone": "+201220987654" },
                { "id": 2, "name": "الزمالك", "address": "شارع 26 يوليو", "phone": "+201223345678" }
            ]
        },
        {
            "id": "g2j4l6n8p0r2t4",
            "name": "ستاربكس",
            "image": "https://images.unsplash.com/photo-1509042239860-f550ce710b93?w=800&q=80",
            "description": "Starbucks is a global coffeehouse chain known for its wide range of coffee drinks and snacks.",
            "menu": [
                {
                    "id": 1,
                    "name": "كاراميل لاتيه",
                    "price": 45,
                    "category": "مشروبات",
                    "description": "قهوة لاتيه مع كراميل وسكر بني.",
                    "image": "https://images.unsplash.com/photo-1461023058943-07fcbe16d735?w=800&q=80",
                    "differents": [
                        { "id": 1, "name": "ساخن", "price": 45 },
                        { "id": 2, "name": "مثلج", "price": 50 }
                    ],
                    "addons": [
                        { "id": 1, "name": "إضافة كريمة", "price": 5 },
                        { "id": 2, "name": "إضافة كراميل", "price": 7 }
                    ]
                }
            ],
            "branches": [
                { "id": 1, "name": "كايرو فيستيفال", "address": "مول كايرو فيستيفال", "phone": "+201234567888" },
                { "id": 2, "name": "سيتي ستارز", "address": "مول سيتي ستارز", "phone": "+201210001112" }
            ]
        },
        {
            "id": "h7k9m1o3q5s7u9",
            "name": "كوستا كوفي",
            "image": "https://images.unsplash.com/photo-1517487881594-2787fef5ebf7?w=800&q=80",
            "description": "Costa Coffee is a popular coffee shop chain known for its wide range of coffee drinks and light meals.",
            "menu": [
                {
                    "id": 1,
                    "name": "كابتشينو",
                    "price": 40,
                    "category": "مشروبات",
                    "description": "قهوة كابتشينو مع رغوة غنية بالحليب.",
                    "image": "https://images.unsplash.com/photo-1572442388796-11668a67e53d?w=800&q=80",
                    "differents": [
                        { "id": 1, "name": "صغير", "price": 35 },
                        { "id": 2, "name": "كبير", "price": 45 }
                    ],
                    "addons": [
                        { "id": 1, "name": "إضافة شوكولاتة", "price": 5 },
                        { "id": 2, "name": "إضافة كراميل", "price": 5 }
                    ]
                }
            ],
            "branches": [
                { "id": 1, "name": "مول العرب", "address": "الشيخ زايد", "phone": "+201332211445" },
                { "id": 2, "name": "كايرو فيستيفال", "address": "مول كايرو فيستيفال", "phone": "+201555888777" }
            ]
        },
        {
            "id": "i4l6n8p0r2t4v6",
            "name": "جرين سوشي",
            "image": "https://images.unsplash.com/photo-1579584425555-c3ce17fd4351?w=800&q=80",
            "description": "Green Sushi is a Japanese restaurant known for its fresh seafood and traditional sushi rolls.",
            "menu": [
                {
                    "id": 1,
                    "name": "California Roll",
                    "price": 90,
                    "category": "سوشي",
                    "description": "لفائف سوشي طازجة مع أفوكادو وسرطان البحر.",
                    "image": "https://images.unsplash.com/photo-1579584425555-c3ce17fd4351?w=800&q=80",
                    "differents": [
                        { "id": 1, "name": "6 قطع", "price": 90 },
                        { "id": 2, "name": "12 قطعة", "price": 150 }
                    ],
                    "addons": [
                        { "id": 1, "name": "صوص صويا", "price": 5 },
                        { "id": 2, "name": "زنجبيل مخلل", "price": 5 }
                    ]
                }
            ],
            "branches": [
                { "id": 1, "name": "المعادي", "address": "كورنيش المعادي", "phone": "+201199887766" },
                { "id": 2, "name": "التجمع", "address": "شارع التسعين", "phone": "+201100223344" }
            ]
        },
        {
            "id": "j1m3o5q7s9u1w3",
            "name": "مطعم شرقي زمان",
            "image": "https://images.unsplash.com/photo-1621996346565-e3dbc646d9a9?w=800&q=80",
            "description": "مطعم شرقي زمان هو متجر 음식 يقدم برائعة مجموعة من الكنب والسلطات.",
            "menu": [
                {
                    "id": 1,
                    "name": "كباب مشوي",
                    "price": 100,
                    "category": "مشويات",
                    "description": "كباب بلدي مشوي على الفحم يقدم مع الأرز والسلطة.",
                    "image": "https://images.unsplash.com/photo-1598515214211-89d3c73ae83b?w=800&q=80",
                    "differents": [
                        { "id": 1, "name": "كباب لحم", "price": 100 },
                        { "id": 2, "name": "كباب دجاج", "price": 90 }
                    ],
                    "addons": [
                        { "id": 1, "name": "سلطة", "price": 10 },
                        { "id": 2, "name": "عيش بلدي", "price": 5 }
                    ]
                }
            ]
        }
    ]}
